tuiet/__init__.py
tuiet/__main__.py
tuiet/app.py
tuiet/config.py
tuiet/constants.py
tuiet/home.py
tuiet/locations.py
tuiet/provider.py
tuiet/themes.py
tuiet/components/autocomplete.py
tuiet/components/barchart.py
tuiet/components/base.py
tuiet/components/button.py
tuiet/components/datatable.py
tuiet/components/fields.py
tuiet/components/indicators.py
tuiet/components/jump_overlay.py
tuiet/components/jumper.py
tuiet/components/modals.py
tuiet/components/percentage_bar.py
tuiet/components/modules/accountmode.py
tuiet/components/modules/datemode.py
tuiet/components/modules/incomemode.py
tuiet/components/modules/insights.py
tuiet/components/modules/records.py
tuiet/components/modules/templates.py
tuiet/models/account.py
tuiet/models/category.py
tuiet/models/person.py
tuiet/models/record.py
tuiet/models/record_template.py
tuiet/models/split.py
tuiet/models/database/app.py
tuiet/models/database/db.py
tuiet/pages/Categories.py
tuiet/queries/accounts.py
tuiet/queries/categories.py
tuiet/queries/persons.py
tuiet/queries/record_templates.py
tuiet/queries/records.py
tuiet/queries/samples.py
tuiet/queries/splits.py
tuiet/queries/utils.py
tuiet/utils/account_forms.py
tuiet/utils/format.py
tuiet/utils/person_forms.py
tuiet/utils/record_forms.py
tuiet/utils/recordtemplate_forms.py
tuiet/utils/user_host.py
tuiet/utils/validation.py
Tuiet-0.1.3.dist-info/LICENSE
Tuiet-0.1.3.dist-info/METADATA
Tuiet-0.1.3.dist-info/WHEEL
Tuiet-0.1.3.dist-info/entry_points.txt
Tuiet-0.1.3.dist-info/top_level.txt
Tuiet-0.1.3.dist-info/RECORD
