Metadata-Version: 2.1
Name: Tuiet
Version: 0.1.3
Summary: Powerful terminal expense tracker.
License: GNU GENERAL PUBLIC LICENSE
Project-URL: Homepage, https://github.com/EnhancedJax/Tuiet
Project-URL: Repository, https://github.com/EnhancedJax/Tuiet
Project-URL: Issues, https://github.com/EnhancedJax/Tuiet/issues
Project-URL: Documentation, https://github.com/EnhancedJax/Tuiet/blob/main/README.md
Keywords: python,cli,expense-tracker,python3,UV,ssh,textual,terminal,tui
Requires-Python: >=3.13
License-File: LICENSE
Requires-Dist: aiohappyeyeballs ==2.4.3
Requires-Dist: aiohttp-jinja2 ==1.6
Requires-Dist: aiohttp ==3.10.10
Requires-Dist: aiosignal ==1.3.1
Requires-Dist: annotated-types ==0.7.0
Requires-Dist: attrs ==24.2.0
Requires-Dist: blinker ==1.8.2
Requires-Dist: click-default-group >=1.2.4
Requires-Dist: click ==8.1.7
Requires-Dist: flask-sqlalchemy ==3.1.1
Requires-Dist: flask ==3.0.3
Requires-Dist: freezegun >=1.5.1
Requires-Dist: frozenlist ==1.5.0
Requires-Dist: idna ==3.10
Requires-Dist: itsdangerous ==2.2.0
Requires-Dist: jinja2 ==3.1.4
Requires-Dist: linkify-it-py ==2.0.3
Requires-Dist: markdown-it-py ==3.0.0
Requires-Dist: markupsafe ==3.0.2
Requires-Dist: mdit-py-plugins ==0.4.2
Requires-Dist: mdurl ==0.1.2
Requires-Dist: msgpack ==1.1.0
Requires-Dist: multidict ==6.1.0
Requires-Dist: platformdirs ==4.3.6
Requires-Dist: plotext ==5.3.2
Requires-Dist: propcache ==0.2.0
Requires-Dist: pydantic-core ==2.23.4
Requires-Dist: pydantic-settings-yaml >=0.2.0
Requires-Dist: pydantic-settings >=2.6.1
Requires-Dist: pydantic ==2.9.2
Requires-Dist: pygments ==2.18.0
Requires-Dist: pytest >=8.3.3
Requires-Dist: pyyaml ==6.0.2
Requires-Dist: rich ==13.9.3
Requires-Dist: sqlalchemy ==2.0.36
Requires-Dist: textual-dev ==1.6.1
Requires-Dist: textual ==0.84.0
Requires-Dist: tomli >=2.0.2
Requires-Dist: typing-extensions ==4.12.2
Requires-Dist: uc-micro-py ==1.0.3
Requires-Dist: werkzeug ==3.0.6
Requires-Dist: xdg-base-dirs >=6.0.2
Requires-Dist: yarl ==1.16.0
